CHANGELOG.rst
LICENSE
MANIFEST.in
README.rst
requirements.txt
setup.py
docs/Makefile
docs/api.rst
docs/conf.py
docs/guide.rst
docs/index.rst
docs/jsonschema.rst
docs/license.rst
docs/requirements.txt
docs/todo.rst
docs/tutorial.rst
docs/_build/html/_sources/api.rst.txt
docs/_build/html/_sources/guide.rst.txt
docs/_build/html/_sources/index.rst.txt
docs/_build/html/_sources/jsonschema.rst.txt
docs/_build/html/_sources/license.rst.txt
docs/_build/html/_sources/tutorial.rst.txt
docs/_build/html/_static/file.png
docs/_build/html/_static/minus.png
docs/_build/html/_static/plus.png
docs/_build/html/_static/css/fonts/fontawesome-webfont.svg
src/miagis/__init__.py
src/miagis/__main__.py
src/miagis/build.py
src/miagis/miagis_schema.py
src/miagis/print_map_layers.py
src/miagis/user_input_checking.py
src/miagis/validate.py
src/miagis.egg-info/PKG-INFO
src/miagis.egg-info/SOURCES.txt
src/miagis.egg-info/dependency_links.txt
src/miagis.egg-info/entry_points.txt
src/miagis.egg-info/requires.txt
src/miagis.egg-info/top_level.txt