Metadata-Version: 2.1
Name: miagis
Version: 1.0.1
Summary: Build and validate GIS metadata.
Home-page: https://github.com/MoseleyBioinformaticsLab/miagis
Author: Travis Thompson
Author-email: ptth222@gmail.com
License: BSD
Keywords: GIS ArcGIS ESRI geospatial
Platform: any
Classifier: Development Status :: 4 - Beta
Classifier: Environment :: Console
Classifier: Intended Audience :: Developers
Classifier: Intended Audience :: Science/Research
Classifier: License :: OSI Approved :: BSD License
Classifier: Operating System :: Microsoft :: Windows
Classifier: Operating System :: MacOS
Classifier: Operating System :: POSIX :: Linux
Classifier: Programming Language :: Python :: 3.7
Classifier: Programming Language :: Python :: 3.8
Classifier: Programming Language :: Python :: 3.9
Classifier: Programming Language :: Python :: 3.10
Classifier: Topic :: Software Development :: Libraries :: Python Modules
License-File: LICENSE
